MANIFEST.in
README.rst
setup.py
aliyun_python_sdk_schedulerx2_test.egg-info/PKG-INFO
aliyun_python_sdk_schedulerx2_test.egg-info/SOURCES.txt
aliyun_python_sdk_schedulerx2_test.egg-info/dependency_links.txt
aliyun_python_sdk_schedulerx2_test.egg-info/requires.txt
aliyun_python_sdk_schedulerx2_test.egg-info/top_level.txt
aliyunsdkschedulerx2/__init__.py
aliyunsdkschedulerx2/request/__init__.py
aliyunsdkschedulerx2/request/v20190430/CreateAppGroupRequest.py
aliyunsdkschedulerx2/request/v20190430/CreateJobRequest.py
aliyunsdkschedulerx2/request/v20190430/DeleteJobRequest.py
aliyunsdkschedulerx2/request/v20190430/DeleteWorkflowRequest.py
aliyunsdkschedulerx2/request/v20190430/DisableJobRequest.py
aliyunsdkschedulerx2/request/v20190430/DisableWorkflowRequest.py
aliyunsdkschedulerx2/request/v20190430/EnableJobRequest.py
aliyunsdkschedulerx2/request/v20190430/EnableWorkflowRequest.py
aliyunsdkschedulerx2/request/v20190430/ExecuteJobRequest.py
aliyunsdkschedulerx2/request/v20190430/ExecuteWorkflowRequest.py
aliyunsdkschedulerx2/request/v20190430/GetJobInfoRequest.py
aliyunsdkschedulerx2/request/v20190430/GetJobInstanceListRequest.py
aliyunsdkschedulerx2/request/v20190430/GetJobInstanceRequest.py
aliyunsdkschedulerx2/request/v20190430/StopInstanceRequest.py
aliyunsdkschedulerx2/request/v20190430/UpdateJobRequest.py
aliyunsdkschedulerx2/request/v20190430/__init__.py